<list>




<m src="http://vsrc.store.qq.com/f0012kxcn4a.flv" stream="true" label="乱世三义 第01集" />
<m src="http://vsrc.store.qq.com/e0012nxpcw7.flv" stream="true" label="乱世三义 第02集" />
<m src="http://vsrc.store.qq.com/j0012hnlgth.flv" stream="true" label="乱世三义 第03集" />
<m src="http://vsrc.store.qq.com/g0012xyuq70.flv" stream="true" label="乱世三义 第04集" />

<m src="http://proxy.player.yy6080.org/baidu/411478/605190972/.flv" label="乱世三义 第05集" />
<m src="http://proxy.player.yy6080.org/baidu/411480/605190972/.flv" label="乱世三义 第06集" />
<m src="http://proxy.player.yy6080.org/baidu/411481/605190972/.flv" label="乱世三义 第07集" />
<m src="http://proxy.player.yy6080.org/baidu/411483/605190972/.flv" label="乱世三义 第08集" />
<m src="http://proxy.player.yy6080.org/baidu/411484/605190972/.flv" label="乱世三义 第09集" />
<m src="http://proxy.player.yy6080.org/baidu/411488/605190972/.flv" label="乱世三义 第10集" />
<m src="http://proxy.player.yy6080.org/baidu/411489/605190972/.flv" label="乱世三义 第11集" />
<m src="http://proxy.player.yy6080.org/baidu/411491/605190972/.flv" label="乱世三义 第12集" />
<m src="http://proxy.player.yy6080.org/baidu/411493/605190972/.flv" label="乱世三义 第13集" />
<m src="http://proxy.player.yy6080.org/baidu/411497/605190972/.flv" label="乱世三义 第14集" />
<m src="http://proxy.player.yy6080.org/baidu/411499/605190972/.flv" label="乱世三义 第15集" />
<m src="http://proxy.player.yy6080.org/baidu/411501/605190972/.flv" label="乱世三义 第16集" />
<m src="http://proxy.player.yy6080.org/baidu/411505/605190972/.flv" label="乱世三义 第17集" />
<m src="http://proxy.player.yy6080.org/baidu/411506/605190972/.flv" label="乱世三义 第18集" />
<m src="http://proxy.player.yy6080.org/baidu/411507/605190972/.flv" label="乱世三义 第19集" />
<m src="http://proxy.player.yy6080.org/baidu/411510/605190972/.flv" label="乱世三义 第20集" />
<m src="http://proxy.player.yy6080.org/baidu/411512/605190972/.flv" label="乱世三义 第21集" />
<m src="http://proxy.player.yy6080.org/baidu/411513/605190972/.flv" label="乱世三义 第22集" />
<m src="http://proxy.player.yy6080.org/baidu/411515/605190972/.flv" label="乱世三义 第23集" />
<m src="http://proxy.player.yy6080.org/baidu/411516/605190972/.flv" label="乱世三义 第24集" />
<m src="http://proxy.player.yy6080.org/baidu/411519/605190972/.flv" label="乱世三义 第25集" />
<m src="http://proxy.player.yy6080.org/baidu/411520/605190972/.flv" label="乱世三义 第26集" />
<m src="http://proxy.player.yy6080.org/baidu/411522/605190972/.flv" label="乱世三义 第27集" />
<m src="http://proxy.player.yy6080.org/baidu/411523/605190972/.flv" label="乱世三义 第28集" />
<m src="http://proxy.player.yy6080.org/baidu/411526/605190972/.flv" label="乱世三义 第29集" />
<m src="http://proxy.player.yy6080.org/baidu/411527/605190972/.flv" label="乱世三义 第30集" />
<m src="http://proxy.player.yy6080.org/baidu/411531/605190972/.flv" label="乱世三义 第31集" />
<m src="http://proxy.player.yy6080.org/baidu/411533/605190972/.flv" label="乱世三义 第32集" />
<m src="http://proxy.player.yy6080.org/baidu/411535/605190972/.flv" label="乱世三义 第33集" />
<m src="http://proxy.player.yy6080.org/baidu/411539/605190972/.flv" label="乱世三义 第34集" />
<m src="http://proxy.player.yy6080.org/baidu/411540/605190972/.flv" label="乱世三义 第35集" />
<m src="http://proxy.player.yy6080.org/baidu/411541/605190972/.flv" label="乱世三义 第36集" />
<m src="http://proxy.player.yy6080.org/baidu/411543/605190972/.flv" label="乱世三义 第37集" />
<m src="http://proxy.player.yy6080.org/baidu/411545/605190972/.flv" label="乱世三义 第38集" />
<m src="http://proxy.player.yy6080.org/baidu/411548/605190972/.flv" label="乱世三义 第39集" />
<m src="http://proxy.player.yy6080.org/baidu/411550/605190972/.flv" label="乱世三义 第40集" />
<m src="http://proxy.player.yy6080.org/baidu/411551/605190972/.flv" label="乱世三义 第41集" />
<m src="http://proxy.player.yy6080.org/baidu/411552/605190972/.flv" label="乱世三义 第42集" />
<m src="http://proxy.player.yy6080.org/baidu/411555/605190972/.flv" label="乱世三义 第43集" />
<m src="http://proxy.player.yy6080.org/baidu/411556/605190972/.flv" label="乱世三义 第44集" />
<m src="http://proxy.player.yy6080.org/baidu/411557/605190972/.flv" label="乱世三义 第45集" />
<m src="http://proxy.player.yy6080.org/baidu/411558/605190972/.flv" label="乱世三义 第46集" />
<m src="http://proxy.player.yy6080.org/baidu/411563/605190972/.flv" label="乱世三义 第47集" />
<m src="http://proxy.player.yy6080.org/baidu/411564/605190972/.flv" label="乱世三义 第48集" />
</list>