<list>
<m src="http://g3.letv.com/2/52/17/202680221.0.flv?start={start_bytes}" stream="true" label="剑勇传说 01(国语)" />
<m src="http://g3.letv.com/3/43/22/203680222.0.flv?start={start_bytes}" stream="true" label="剑勇传说 02(国语)" />
<m src="http://g3.letv.com/5/25/32/205680224.0.flv?start={start_bytes}" stream="true" label="剑勇传说 03(国语)" />
<m src="http://g3.letv.com/2/36/82/202680227.0.flv?start={start_bytes}" stream="true" label="剑勇传说 04(国语)" />
<m src="http://g3.letv.com/4/18/92/204680229.0.flv?start={start_bytes}" stream="true" label="剑勇传说 05(国语)" />
<m src="http://g3.letv.com/6/14/95/206680231.0.flv?start={start_bytes}" stream="true" label="剑勇传说 06(国语)" />
<m src="http://g3.letv.com/2/49/104/202680233.0.flv?start={start_bytes}" stream="true" label="剑勇传说 07(国语)" />
<m src="http://g3.letv.com/3/40/109/203680234.0.flv?start={start_bytes}" stream="true" label="剑勇传说 08(国语)" />
<m src="http://g3.letv.com/4/31/1/204680235.0.flv?start={start_bytes}" stream="true" label="剑勇传说 09(国语)" />
<m src="http://g3.letv.com/5/7/42/205680236.0.flv?start={start_bytes}" stream="true" label="剑勇传说 10(国语)" />
<m src="http://g3.letv.com/6/51/46/206680237.0.flv?start={start_bytes}" stream="true" label="剑勇传说 11(国语)" />
<m src="http://g3.letv.com/2/33/56/202680239.0.flv?start={start_bytes}" stream="true" label="剑勇传说 12(国语)" />
<m src="http://g3.letv.com/1/17/52/201682290.0.flv?start={start_bytes}" stream="true" label="剑勇传说 13(国语)" />
<m src="http://g3.letv.com/3/52/61/203682292.0.flv?start={start_bytes}" stream="true" label="剑勇传说 14(国语)" />
<m src="http://g3.letv.com/5/34/71/205682294.0.flv?start={start_bytes}" stream="true" label="剑勇传说 15(国语)" />
<m src="http://g3.letv.com/3/36/13/203682298.0.flv?start={start_bytes}" stream="true" label="剑勇传说 16(国语)" />
<m src="http://g3.letv.com/2/28/102/202682303.0.flv?start={start_bytes}" stream="true" label="剑勇传说 17(国语)" />
<m src="http://g3.letv.com/1/21/49/201682308.0.flv?start={start_bytes}" stream="true" label="剑勇传说 18(国语)" />
<m src="http://g3.letv.com/3/3/112/203682310.0.flv?start={start_bytes}" stream="true" label="剑勇传说 19(国语)" />
<m src="http://g3.letv.com/4/47/3/204682311.0.flv?start={start_bytes}" stream="true" label="剑勇传说 20(国语)" />
<m src="http://g3.letv.com/6/29/13/206682313.0.flv?start={start_bytes}" stream="true" label="剑勇传说 21(国语)" />
<m src="http://g3.letv.com/1/20/18/201682314.0.flv?start={start_bytes}" stream="true" label="剑勇传说 22(国语)" />
<m src="http://g3.letv.com/6/13/78/206682319.0.flv?start={start_bytes}" stream="true" label="剑勇传说 23(国语)" />
<m src="http://g3.letv.com/5/33/40/205682330.0.flv?start={start_bytes}" stream="true" label="剑勇传说 24(国语)" />
<m src="http://g3.letv.com/3/48/4/203682340.0.flv?start={start_bytes}" stream="true" label="剑勇传说 25(国语)" />
<m src="http://g3.letv.com/3/31/38/203682352.0.flv?start={start_bytes}" stream="true" label="剑勇传说 26(国语)" />
<m src="http://g3.letv.com/5/49/92/205682984.0.flv?start={start_bytes}" stream="true" label="剑勇传说 27(国语)" />
<m src="http://g3.letv.com/2/43/63/202682999.0.flv?start={start_bytes}" stream="true" label="剑勇传说 28(国语)" />
<m src="http://g3.letv.com/3/29/44/203683018.0.flv?start={start_bytes}" stream="true" label="剑勇传说 29(国语)" />
<m src="http://g3.letv.com/1/7/57/201683022.0.flv?start={start_bytes}" stream="true" label="剑勇传说 30(国语)" />
<m src="http://g3.letv.com/2/35/13/202683029.0.flv?start={start_bytes}" stream="true" label="剑勇传说 31(国语)" />
<m src="http://g3.letv.com/5/22/21/205683032.0.flv?start={start_bytes}" stream="true" label="剑勇传说 32(国语)" />
<m src="http://g3.letv.com/4/15/81/204683037.0.flv?start={start_bytes}" stream="true" label="剑勇传说 33(国语)" />
<m src="http://g3.letv.com/6/50/90/206683039.0.flv?start={start_bytes}" stream="true" label="剑勇传说 34(国语)" />
<m src="http://g3.letv.com/6/31/69/206683057.0.flv?start={start_bytes}" stream="true" label="剑勇传说 35(国语)" />
<m src="http://g3.letv.com/1/22/60/201683220.0.flv?start={start_bytes}" stream="true" label="剑勇传说 36(国语)" />
<m src="http://g3.letv.com/2/7/13/202683245.0.flv?start={start_bytes}" stream="true" label="剑勇传说 37(国语)" />
<m src="http://g3.letv.com/6/6/95/206683261.0.flv?start={start_bytes}" stream="true" label="剑勇传说 38(国语)" />
<m src="http://g3.letv.com/6/3/69/206683273.0.flv?start={start_bytes}" stream="true" label="剑勇传说 39(国语)" />
<m src="http://g3.letv.com/2/36/23/202683281.0.flv?start={start_bytes}" stream="true" label="剑勇传说 40(国语)" />
<m src="http://g3.letv.com/5/38/34/205683428.0.flv?start={start_bytes}" stream="true" label="剑勇传说 41(国语)" />
<m src="http://g3.letv.com/3/53/111/203683438.0.flv?start={start_bytes}" stream="true" label="剑勇传说 42(国语)" />
<m src="http://g3.letv.com/5/33/66/205683446.0.flv?start={start_bytes}" stream="true" label="剑勇传说 43(国语)" />
<m src="http://g3.letv.com/3/47/112/203683462.0.flv?start={start_bytes}" stream="true" label="剑勇传说 44(国语)" />
<m src="http://g3.letv.com/3/44/86/203683474.0.flv?start={start_bytes}" stream="true" label="剑勇传说 45(国语)" />
<m src="http://g3.letv.com/6/15/46/206683483.0.flv?start={start_bytes}" stream="true" label="剑勇传说 46(国语)" />
<m src="http://g3.letv.com/6/51/79/206683495.0.flv?start={start_bytes}" stream="true" label="剑勇传说 47(国语)" />
<m src="http://g3.letv.com/5/28/91/205683500.0.flv?start={start_bytes}" stream="true" label="剑勇传说 48(国语)" />
<m src="http://g3.letv.com/6/3/48/206683507.0.flv?start={start_bytes}" stream="true" label="剑勇传说 49(国语)" />
<m src="http://g3.letv.com/6/39/81/206683519.0.flv?start={start_bytes}" stream="true" label="剑勇传说 50(国语)" />
<m src="http://g3.letv.com/5/43/108/205683536.0.flv?start={start_bytes}" stream="true" label="剑勇传说 51(国语)" />
<m src="http://g3.letv.com/2/29/32/202683545.0.flv?start={start_bytes}" stream="true" label="剑勇传说 52(国语)" />
</list>